LICENSE.md
MANIFEST.in
README.md
setup.py
hass_frontend/0477696d8c35df28ad65.chunk.js
hass_frontend/0477696d8c35df28ad65.chunk.js.gz
hass_frontend/0477696d8c35df28ad65.chunk.js.map
hass_frontend/06ef688c0e346d0dc2c7.chunk.js
hass_frontend/06ef688c0e346d0dc2c7.chunk.js.LICENSE
hass_frontend/06ef688c0e346d0dc2c7.chunk.js.gz
hass_frontend/06ef688c0e346d0dc2c7.chunk.js.map
hass_frontend/0c48581df6f665e245d5.chunk.js
hass_frontend/0c48581df6f665e245d5.chunk.js.LICENSE
hass_frontend/0c48581df6f665e245d5.chunk.js.gz
hass_frontend/0c48581df6f665e245d5.chunk.js.map
hass_frontend/11ec51b1619205a83fbe.chunk.js
hass_frontend/11ec51b1619205a83fbe.chunk.js.LICENSE
hass_frontend/11ec51b1619205a83fbe.chunk.js.gz
hass_frontend/11ec51b1619205a83fbe.chunk.js.map
hass_frontend/15fbf3992f3b731b5dd0.chunk.js
hass_frontend/15fbf3992f3b731b5dd0.chunk.js.gz
hass_frontend/15fbf3992f3b731b5dd0.chunk.js.map
hass_frontend/24769dd0922fb6ee5daa.chunk.js
hass_frontend/24769dd0922fb6ee5daa.chunk.js.LICENSE
hass_frontend/24769dd0922fb6ee5daa.chunk.js.gz
hass_frontend/24769dd0922fb6ee5daa.chunk.js.map
hass_frontend/2719e6e696ccebaf1ddc.chunk.js
hass_frontend/2719e6e696ccebaf1ddc.chunk.js.gz
hass_frontend/2719e6e696ccebaf1ddc.chunk.js.map
hass_frontend/28a71be6877e22cb7b41.chunk.js
hass_frontend/28a71be6877e22cb7b41.chunk.js.gz
hass_frontend/28a71be6877e22cb7b41.chunk.js.map
hass_frontend/2f9670ff15079ae94740.chunk.js
hass_frontend/2f9670ff15079ae94740.chunk.js.gz
hass_frontend/2f9670ff15079ae94740.chunk.js.map
hass_frontend/35f10815f19b9c61fb68.chunk.js
hass_frontend/35f10815f19b9c61fb68.chunk.js.LICENSE
hass_frontend/35f10815f19b9c61fb68.chunk.js.gz
hass_frontend/35f10815f19b9c61fb68.chunk.js.map
hass_frontend/37a2cf6ad638ba8e9e48.chunk.js
hass_frontend/37a2cf6ad638ba8e9e48.chunk.js.LICENSE
hass_frontend/37a2cf6ad638ba8e9e48.chunk.js.gz
hass_frontend/37a2cf6ad638ba8e9e48.chunk.js.map
hass_frontend/403da168cf72cb31742d.chunk.js
hass_frontend/403da168cf72cb31742d.chunk.js.LICENSE
shimao_nosidebar_frontend.egg-info/PKG-INFO
shimao_nosidebar_frontend.egg-info/SOURCES.txt
shimao_nosidebar_frontend.egg-info/dependency_links.txt
shimao_nosidebar_frontend.egg-info/not-zip-safe
shimao_nosidebar_frontend.egg-info/requires.txt
shimao_nosidebar_frontend.egg-info/top_level.txt