Metadata-Version: 1.0
Name: shimao-nosidebar-frontend
Version: 20180926.0
Summary: Shimao smart
Home-page: https://github.com/home-assistant/home-assistant-polymer
Author: shi mao fengsh
Author-email: fengsh998@163.com
License: Apache License 2.0
Platform: UNKNOWN
